mypack/__init__.py
mypack/np_utils.py
mypack/pd_utils.py
mypack/plot_utils.py
tests/__init__.py
tests/test_lib.py
renan-0.0.1.dist-info/LICENSE
renan-0.0.1.dist-info/METADATA
renan-0.0.1.dist-info/WHEEL
renan-0.0.1.dist-info/top_level.txt
renan-0.0.1.dist-info/RECORD
